mcp_server_browser_use/__init__.py
mcp_server_browser_use/__main__.py
mcp_server_browser_use/cli.py
mcp_server_browser_use/config.py
mcp_server_browser_use/server.py
mcp_server_browser_use/_internal/__init__.py
mcp_server_browser_use/_internal/agent/__init__.py
mcp_server_browser_use/_internal/agent/browser_use/browser_use_agent.py
mcp_server_browser_use/_internal/agent/deep_research/deep_research_agent.py
mcp_server_browser_use/_internal/browser/__init__.py
mcp_server_browser_use/_internal/browser/custom_browser.py
mcp_server_browser_use/_internal/browser/custom_context.py
mcp_server_browser_use/_internal/controller/__init__.py
mcp_server_browser_use/_internal/controller/custom_controller.py
mcp_server_browser_use/_internal/utils/__init__.py
mcp_server_browser_use/_internal/utils/config.py
mcp_server_browser_use/_internal/utils/llm_provider.py
mcp_server_browser_use/_internal/utils/mcp_client.py
mcp_server_browser_use/_internal/utils/utils.py
mcp_server_browser_use-0.1.9.dist-info/METADATA
mcp_server_browser_use-0.1.9.dist-info/WHEEL
mcp_server_browser_use-0.1.9.dist-info/entry_points.txt
mcp_server_browser_use-0.1.9.dist-info/licenses/LICENSE
mcp_server_browser_use-0.1.9.dist-info/RECORD
