Metadata-Version: 2.4
Name: mcp_server_browser_use
Version: 0.1.9
Summary: MCP server for browser-use
Author: Igor Tarasenko
License: MIT
License-File: LICENSE
Classifier: Development Status :: 4 - Beta
Classifier: Operating System :: OS Independent
Classifier: Programming Language :: Python :: 3
Classifier: Programming Language :: Python :: 3.11
Requires-Python: >=3.11
Requires-Dist: browser-use==0.1.41
Requires-Dist: json-repair
Requires-Dist: langchain-community
Requires-Dist: langchain-ibm==0.3.10
Requires-Dist: langchain-mcp-adapters==0.0.9
Requires-Dist: langchain-mistralai==0.2.4
Requires-Dist: langgraph==0.3.34
Requires-Dist: maincontentextractor==0.0.4
Requires-Dist: mcp>=1.6.0
Requires-Dist: pydantic-settings>=2.0.0
Requires-Dist: pyperclip==1.9.0
Requires-Dist: typer>=0.12.0
